README.rst
setup.cfg
setup.py
./__init__.py
./configuration.py
./configuration.xml
./index.py
./index.xml
./tryton.cfg
./tests/__init__.py
./tests/test_elastic_search.py
./view/configuration_form.xml
./view/document_type_form.xml
./view/document_type_list.xml
./view/index_backlog_form.xml
./view/index_backlog_list.xml
trytond_elastic_search.egg-info/PKG-INFO
trytond_elastic_search.egg-info/SOURCES.txt
trytond_elastic_search.egg-info/dependency_links.txt
trytond_elastic_search.egg-info/entry_points.txt
trytond_elastic_search.egg-info/not-zip-safe
trytond_elastic_search.egg-info/requires.txt
trytond_elastic_search.egg-info/top_level.txt